trace_selector/__init__.py
trace_selector/__main__.py
trace_selector/assets/add.svg
trace_selector/assets/back.svg
trace_selector/assets/home.svg
trace_selector/assets/keep.svg
trace_selector/assets/open.svg
trace_selector/assets/peak.svg
trace_selector/assets/save.svg
trace_selector/assets/settings.svg
trace_selector/assets/trash.svg
trace_selector/detection/__init__.py
trace_selector/detection/model_wraper.py
trace_selector/detection/model_zoo.py
trace_selector/detection/peak_detection.py
trace_selector/gui/__init__.py
trace_selector/gui/add_window.py
trace_selector/gui/api.py
trace_selector/gui/gui.py
trace_selector/gui/settingswindow.py
trace_selector/settings/default_settings.json
trace_selector/utils/__init__.py
trace_selector/utils/configuration.py
trace_selector/utils/export.py
trace_selector/utils/hash.py
trace_selector/utils/normalization.py
trace_selector/utils/plot.py
trace_selector/utils/threshold.py
trace_selector/utils/trace_data.py
trace_selector/utils/post_selection/__init__.py
trace_selector/utils/post_selection/decay_compute.py
trace_selector/utils/post_selection/failure_rate.py
trace_selector-1.0.2.dist-info/METADATA
trace_selector-1.0.2.dist-info/WHEEL
trace_selector-1.0.2.dist-info/licenses/LICENSE
trace_selector-1.0.2.dist-info/RECORD
