Metadata-Version: 2.4
Name: trace-selector
Version: 1.0.2
Summary: Small internal package for post-selection of Glutmate/Calcium signal responses.
Author-email: Stephan Weissbach <s.weissbach@uni-mainz.de>
License-File: LICENSE
Requires-Python: >=3.9
Requires-Dist: numpy>=1.26.1
Requires-Dist: openpyxl>=3.1.2
Requires-Dist: pandas>=2.1.1
Requires-Dist: platformdirs>=4
Requires-Dist: plotly>=5.17.0
Requires-Dist: pyqt6-webengine>=6.6.0
Requires-Dist: requests>=2.31.0
Requires-Dist: scipy>=1.11.3
Requires-Dist: torch>=2.1.1
